keepalived_api-0.0.2.dist-info/licenses/LICENSE
keepalived_config/__init__.py
keepalived_config/keepalived_config.py
keepalived_config/keepalived_config_base.py
keepalived_config/keepalived_config_block.py
keepalived_config/keepalived_config_comment.py
keepalived_config/keepalived_config_constants.py
keepalived_config/keepalived_config_exceptions.py
keepalived_config/keepalived_config_manager.py
keepalived_config/keepalived_config_param.py
keepalived_config/keepalived_config_parser.py
keepalived_config/keepalived_config_result.py
keepalived_config/keepalived_config_templates.py
keepalived_config/keepalived_config_types.py
keepalived_config/keepalived_config_validator.py
keepalived_config/keepalived_config_virtual_server.py
keepalived_config/keepalived_config_vrrp.py
keepalived_api-0.0.2.dist-info/METADATA
keepalived_api-0.0.2.dist-info/WHEEL
keepalived_api-0.0.2.dist-info/top_level.txt
keepalived_api-0.0.2.dist-info/RECORD
