Metadata-Version: 2.4
Name: keepalived-api
Version: 0.0.2
Home-page: https://github.com/charnet1019/keepalived-api
Author: charnet1019
License: GNU GENERAL PUBLIC LICENSE
Requires-Python: >=3.10
License-File: LICENSE
Dynamic: author
Dynamic: description
Dynamic: description-content-type
Dynamic: home-page
Dynamic: license
Dynamic: license-file
Dynamic: requires-python
